{"ok":true,"data_date":"2026-07-14","fetched_at":"2026-07-14 10:39:55","source":"yfinance","error":null,"data":{"cards":[{"symbol":"^TWII","name":"加權指數","short":"TAIEX","close":44737.95,"prev":45380.52,"change":-642.57,"pct":-1.42,"date":"2026-07-14"},{"symbol":"^SOX","name":"費城半導體","short":"SOX","close":12347.78,"prev":12967.16,"change":-619.38,"pct":-4.78,"date":"2026-07-13"},{"symbol":"^GSPC","name":"S&P 500","short":"S&P500","close":7515.34,"prev":7575.39,"change":-60.05,"pct":-0.79,"date":"2026-07-13"},{"symbol":"TSM","name":"台積電 ADR","short":"TSM","close":421.58,"prev":434.11,"change":-12.53,"pct":-2.89,"date":"2026-07-13"},{"symbol":"^N225","name":"日經 225","short":"N225","close":67743.5,"prev":67242.73,"change":500.77,"pct":0.74,"date":"2026-07-14"},{"symbol":"^VIX","name":"VIX 恐慌","short":"VIX","close":17.3,"prev":17.16,"change":0.14,"pct":0.82,"date":"2026-07-14"},{"symbol":"NVDA","name":"NVIDIA","short":"NVDA","close":203.53,"prev":210.96,"change":-7.43,"pct":-3.52,"date":"2026-07-13"}]}}